pyunit_ner/__init__.py
pyunit_ner/ner.py
pyunit_ner/transformer_encoder.py
pyunit_ner/vocab.py
pyunit_ner-2021.8.2.dist-info/METADATA
pyunit_ner-2021.8.2.dist-info/WHEEL
pyunit_ner-2021.8.2.dist-info/top_level.txt
pyunit_ner-2021.8.2.dist-info/zip-safe
pyunit_ner-2021.8.2.dist-info/RECORD
