Metadata-Version: 2.1
Name: pyunit-ner
Version: 2021.8.2
Summary: 百度实体抽取模型
Home-page: https://github.com/PyUnit/pyunit-ner
Author: Jtyoui
Author-email: jtyoui@qq.com
License: MIT Licence
Platform: any
Classifier: Programming Language :: Python :: 3
Classifier: License :: OSI Approved :: MIT License
Classifier: Operating System :: OS Independent
Requires-Dist: paddlepaddle (==1.8.5)
